[{"__type__":"sp.SkeletonData","_name":"role_fish_17","_rawFiles":["raw-skeleton.json"],"_skeletonJson":{"skeleton":{"hash":"Q7hu1n7GhHcwHLlASb2m+lkoQDY","spine":"3.6.53","width":119,"height":94,"images":"./images/"},"bones":[{"name":"root"},{"name":"yu","parent":"root","x":2.84,"y":36.6}],"slots":[{"name":"yu","bone":"yu","attachment":"yu"}],"skins":{"default":{"yu":{"yu":{"x":2.14,"y":7.31,"width":119,"height":94}}}},"animations":{"role_move":{"bones":{"yu":{"translate":[{"time":0,"x":0,"y":0,"curve":"stepped"},{"time":1.3333,"x":0,"y":0}],"scale":[{"time":0,"x":1,"y":1},{"time":0.6667,"x":0.91,"y":0.979},{"time":1.3333,"x":1,"y":1}]}}}}},"_atlasText":"\nrole_fish_17.png\nsize: 128,128\nformat: RGBA8888\nfilter: Linear,Linear\nrepeat: none\nyu\n  rotate: false\n  xy: 2, 2\n  size: 115, 90\n  orig: 119, 94\n  offset: 2, 2\n  index: -1\n","atlasUrl":{"__uuid__":"91xITMVqxBALAzp1LshGfF"},"textures":[{"__uuid__":"08yiTAn7ZLbbzqb7RyRLr3"}]},{"__type__":"cc.SpriteFrame","content":{"name":"role_fish_17","texture":"9erlVlLMJG0pdEUTrietlY","rect":[0,0,115,90],"offset":[0,0],"originalSize":[115,90]}},[{"__type__":"cc.Prefab","_name":"fish_11","data":{"__id__":1},"asyncLoadAssets":null},{"__type__":"cc.Node","_name":"fish","_children":[{"__id__":2}],"_components":[{"__type__":"5efddKa6VJBXqLaXx/6lBpf","node":{"__id__":1},"fishNode":{"__id__":2},"ani":{"__id__":4}}],"_prefab":{"__type__":"cc.PrefabInfo","root":{"__id__":1},"asset":{"__uuid__":"eadgW0gS5L5IucLyaEf7kx"},"fileId":"c4cHflozxPL74syR05F7U6"},"_anchorPoint":{"__type__":"cc.Vec2","y":0.5},"_contentSize":{"__type__":"cc.Size","width":57.5,"height":46},"_position":{"__type__":"cc.Vec2","x":-121.8,"y":-574.2},"groupIndex":2},{"__type__":"cc.Node","_name":"fishNode","_parent":{"__id__":1},"_children":[{"__id__":3}],"_components":[{"__type__":"cc.BoxCollider","node":{"__id__":2},"_offset":{"__type__":"cc.Vec2","x":28.75,"y":20},"_size":{"__type__":"cc.Size","width":57.5,"height":45}},{"__type__":"cc.Sprite","node":{"__id__":2},"_spriteFrame":{"__uuid__":"e7lhR4cT1EMr/o3GisdQlK"},"_sizeMode":0}],"_prefab":{"__type__":"cc.PrefabInfo","root":{"__id__":1},"asset":{"__uuid__":"eadgW0gS5L5IucLyaEf7kx"},"fileId":"42E0d7S+BAjaOgSAe+m/c5"},"_anchorPoint":{"__type__":"cc.Vec2","y":0.5},"_contentSize":{"__type__":"cc.Size","width":77.1,"height":65.2},"_position":{"__type__":"cc.Vec2","x":0.9,"y":0.4},"groupIndex":2},{"__type__":"cc.Node","_name":"role_fish_17","_parent":{"__id__":2},"_components":[{"__id__":4}],"_prefab":{"__type__":"cc.PrefabInfo","root":{"__id__":1},"asset":{"__uuid__":"eadgW0gS5L5IucLyaEf7kx"},"fileId":"1e+VMo0oJMAZlufRtx+GjD"},"_scaleX":0.75,"_scaleY":0.75,"_position":{"__type__":"cc.Vec2","x":35.3,"y":-34.2}},{"__type__":"sp.Skeleton","node":{"__id__":3},"defaultAnimation":"role_move","_N$skeletonData":{"__uuid__":"7cs4ks9rJChLjicYa+ADbI"}}]]